Metadata-Version: 1.2
Name: showTree
Version: 1.0.0
Summary: a way to make your life easier
Home-page: https://github.com/batestin1/
Author: bates
Author-email: bates@mailer.com.br
License: UNKNOWN
Project-URL: Codigo fonte, https://github.com/batestin1/
Project-URL: Download, https://github.com/batestin1/
Keywords: a way to make your life easier
Platform: UNKNOWN
